Metadata-Version: 2.1
Name: sqlhild
Version: 0.1.1
Summary: sqlhild SQLifies everything
Home-page: https://github.com/willemt/sqlhild
Author: willemt
Author-email: himself@willemthiart.com
License: BSD
Keywords: development logging
Platform: UNKNOWN
Classifier: Development Status :: 3 - Alpha
Classifier: Intended Audience :: Developers
Classifier: Topic :: System :: Logging
Classifier: License :: OSI Approved :: BSD License
Classifier: Programming Language :: Python :: 3.7
Requires-Dist: Pygments
Requires-Dist: SQLAlchemy
Requires-Dist: addict
Requires-Dist: antlr4-python3-runtime
Requires-Dist: astor
Requires-Dist: attrs
Requires-Dist: autopep8
Requires-Dist: docopt
Requires-Dist: docutils
Requires-Dist: lmdb
Requires-Dist: matchpy
Requires-Dist: numba
Requires-Dist: numpy
Requires-Dist: protlib
Requires-Dist: psutil
Requires-Dist: pygments
Requires-Dist: tablib
Requires-Dist: terminaltables
Requires-Dist: typeguard
